terminaltools/__init__.py
terminaltools-0.1.1.dist-info/LICENSE
terminaltools-0.1.1.dist-info/METADATA
terminaltools-0.1.1.dist-info/WHEEL
terminaltools-0.1.1.dist-info/top_level.txt
terminaltools-0.1.1.dist-info/RECORD
