Metadata-Version: 2.1
Name: terminaltools
Version: 0.1.1
Summary: Some personal tools for working with the terminal in Python.
Home-page: https://github.com/ericli3690/terminaltools
Author: Eric Li
Author-email: ericli3690@gmail.com
Classifier: Programming Language :: Python :: 3
Classifier: License :: OSI Approved :: MIT License
Classifier: Operating System :: OS Independent
Requires-Python: >=3.8.0
License-File: LICENSE
